{
    "swagger": "2.0",
    "info": {
        "contact": {}
    },
    "paths": {
        "/attribute/{id}": {
            "get": {
                "security": [
                    {
                        "ApiKeyAuth": []
                    }
                ],
                "description": "get Attribute by Id",
                "consumes": [
                    "application/json"
                ],
                "produces": [
                    "application/json"
                ],
                "tags": [
                    "Attribute"
                ],
                "summary": "Get A Attribute",
                "parameters": [
                    {
                        "type": "integer",
                        "description": "Attribute ID",
                        "name": "id",
                        "in": "path",
                        "required": true
                    },
                    {
                        "type": "string",
                        "description": "Authorization",
                        "name": "Authorization",
                        "in": "header"
                    }
                ],
                "responses": {
                    "200": {
                        "description": "OK",
                        "schema": {
                            "$ref": "#/definitions/db.CategoryAttribute"
                        }
                    }
                }
            },
            "patch": {
                "security": [
                    {
                        "ApiKeyAuth": []
                    }
                ],
                "description": "Update Attribute by Id",
                "consumes": [
                    "application/json"
                ],
                "produces": [
                    "application/json"
                ],
                "tags": [
                    "Attribute"
                ],
                "summary": "Update A Attribute",
                "parameters": [
                    {
                        "type": "integer",
                        "description": "Attribute ID",
                        "name": "id",
                        "in": "path",
                        "required": true
                    },
                    {
                        "description": "Update Attributes Params",
                        "name": "id",
                        "in": "body",
                        "required": true,
                        "schema": {
                            "$ref": "#/definitions/db.UpdateAttributeParams"
                        }
                    },
                    {
                        "type": "string",
                        "description": "Authorization",
                        "name": "Authorization",
                        "in": "header"
                    }
                ],
                "responses": {
                    "200": {
                        "description": "OK",
                        "schema": {
                            "$ref": "#/definitions/db.CategoryAttribute"
                        }
                    }
                }
            }
        },
        "/attributes": {
            "get": {
                "description": "get Attribute by Id",
                "consumes": [
                    "application/json"
                ],
                "produces": [
                    "application/json"
                ],
                "tags": [
                    "Attribute"
                ],
                "summary": "List Attributes",
                "responses": {
                    "200": {
                        "description": "OK",
                        "schema": {
                            "type": "array",
                            "items": {
                                "$ref": "#/definitions/db.CategoryAttribute"
                            }
                        }
                    }
                }
            }
        },
        "/categories": {
            "get": {
                "description": "get Category by Id",
                "consumes": [
                    "application/json"
                ],
                "produces": [
                    "application/json"
                ],
                "tags": [
                    "Category"
                ],
                "summary": "List Categories",
                "responses": {
                    "200": {
                        "description": "OK",
                        "schema": {
                            "type": "array",
                            "items": {
                                "$ref": "#/definitions/db.Category"
                            }
                        }
                    }
                }
            },
            "post": {
                "description": "post Category by Id",
                "consumes": [
                    "application/json"
                ],
                "produces": [
                    "application/json"
                ],
                "tags": [
                    "Category"
                ],
                "summary": "Create A Category",
                "parameters": [
                    {
                        "type": "integer",
                        "description": "Category ID",
                        "name": "id",
                        "in": "path",
                        "required": true
                    },
                    {
                        "type": "string",
                        "description": "Authorization",
                        "name": "Authorization",
                        "in": "header"
                    },
                    {
                        "description": "Category Params",
                        "name": "id",
                        "in": "body",
                        "required": true,
                        "schema": {
                            "$ref": "#/definitions/handler.CategoryReq"
                        }
                    }
                ],
                "responses": {
                    "200": {
                        "description": "OK",
                        "schema": {
                            "type": "string"
                        }
                    }
                }
            }
        },
        "/categories/:id": {
            "patch": {
                "description": "post Category by Id",
                "consumes": [
                    "application/json"
                ],
                "produces": [
                    "application/json"
                ],
                "tags": [
                    "Category"
                ],
                "summary": "Update A Category",
                "parameters": [
                    {
                        "type": "integer",
                        "description": "Category ID",
                        "name": "id",
                        "in": "path",
                        "required": true
                    },
                    {
                        "type": "string",
                        "description": "Authorization",
                        "name": "Authorization",
                        "in": "header"
                    },
                    {
                        "description": "Category Params",
                        "name": "id",
                        "in": "body",
                        "required": true,
                        "schema": {
                            "$ref": "#/definitions/handler.CategoryReq"
                        }
                    }
                ],
                "responses": {
                    "200": {
                        "description": "OK",
                        "schema": {
                            "type": "string"
                        }
                    }
                }
            }
        },
        "/categories/:id/attributes": {
            "get": {
                "description": "get Category by Id",
                "consumes": [
                    "application/json"
                ],
                "produces": [
                    "application/json"
                ],
                "tags": [
                    "Category"
                ],
                "summary": "List All Attributes In Category",
                "parameters": [
                    {
                        "type": "integer",
                        "description": "Category ID",
                        "name": "id",
                        "in": "path",
                        "required": true
                    }
                ],
                "responses": {
                    "200": {
                        "description": "OK",
                        "schema": {
                            "type": "array",
                            "items": {
                                "$ref": "#/definitions/db.Category"
                            }
                        }
                    }
                }
            },
            "post": {
                "description": "post Attribute by Id",
                "consumes": [
                    "application/json"
                ],
                "produces": [
                    "application/json"
                ],
                "tags": [
                    "Attribute"
                ],
                "summary": "Create A Attribute",
                "parameters": [
                    {
                        "type": "integer",
                        "description": "Attribute ID",
                        "name": "id",
                        "in": "path",
                        "required": true
                    },
                    {
                        "description": "Category Params",
                        "name": "id",
                        "in": "body",
                        "required": true,
                        "schema": {
                            "$ref": "#/definitions/db.CreateCategoryAttributeParams"
                        }
                    },
                    {
                        "type": "string",
                        "description": "Authorization",
                        "name": "Authorization",
                        "in": "header"
                    }
                ],
                "responses": {
                    "200": {
                        "description": "OK",
                        "schema": {
                            "$ref": "#/definitions/db.CategoryAttribute"
                        }
                    }
                }
            }
        },
        "/categories/:id/background": {
            "post": {
                "security": [
                    {
                        "ApiKeyAuth": []
                    }
                ],
                "description": "Upload An Image for the Product with This ID",
                "consumes": [
                    "application/json"
                ],
                "produces": [
                    "application/json"
                ],
                "tags": [
                    "Product"
                ],
                "summary": "Upload Image And Set As Category Background",
                "parameters": [
                    {
                        "type": "integer",
                        "description": "Category ID",
                        "name": "id",
                        "in": "path",
                        "required": true
                    },
                    {
                        "type": "string",
                        "description": "Authorization",
                        "name": "Authorization",
                        "in": "header"
                    },
                    {
                        "type": "file",
                        "description": "image to upload",
                        "name": "image",
                        "in": "formData",
                        "required": true
                    }
                ],
                "responses": {
                    "200": {
                        "description": "OK",
                        "schema": {
                            "$ref": "#/definitions/handler.CategoryRes"
                        }
                    }
                }
            }
        },
        "/categories/:id/banner": {
            "post": {
                "security": [
                    {
                        "ApiKeyAuth": []
                    }
                ],
                "description": "Upload An Image for the Product with This ID",
                "consumes": [
                    "application/json"
                ],
                "produces": [
                    "application/json"
                ],
                "tags": [
                    "Product"
                ],
                "summary": "Upload Image And Set As Category Banner",
                "parameters": [
                    {
                        "type": "integer",
                        "description": "Category ID",
                        "name": "id",
                        "in": "path",
                        "required": true
                    },
                    {
                        "type": "string",
                        "description": "Authorization",
                        "name": "Authorization",
                        "in": "header"
                    },
                    {
                        "type": "file",
                        "description": "image to upload",
                        "name": "image",
                        "in": "formData",
                        "required": true
                    }
                ],
                "responses": {
                    "200": {
                        "description": "OK",
                        "schema": {
                            "$ref": "#/definitions/handler.CategoryRes"
                        }
                    }
                }
            }
        },
        "/categories/:id/parent/remove": {
            "delete": {
                "description": "Remove parent category from current category",
                "consumes": [
                    "application/json"
                ],
                "produces": [
                    "application/json"
                ],
                "tags": [
                    "Category"
                ],
                "summary": "Remove parent from category",
                "parameters": [
                    {
                        "type": "integer",
                        "description": "Category ID",
                        "name": "id",
                        "in": "path",
                        "required": true
                    },
                    {
                        "type": "string",
                        "description": "Authorization",
                        "name": "Authorization",
                        "in": "header"
                    },
                    {
                        "description": "Category Params",
                        "name": "id",
                        "in": "body",
                        "required": true,
                        "schema": {
                            "$ref": "#/definitions/handler.CategoryReq"
                        }
                    }
                ],
                "responses": {
                    "200": {
                        "description": "OK",
                        "schema": {
                            "type": "string"
                        }
                    }
                }
            }
        },
        "/categories/:id/parent/set": {
            "post": {
                "description": "post Category by Id",
                "consumes": [
                    "application/json"
                ],
                "produces": [
                    "application/json"
                ],
                "tags": [
                    "Category"
                ],
                "summary": "Update A Category",
                "parameters": [
                    {
                        "type": "integer",
                        "description": "Category ID",
                        "name": "id",
                        "in": "path",
                        "required": true
                    },
                    {
                        "type": "string",
                        "description": "Authorization",
                        "name": "Authorization",
                        "in": "header"
                    },
                    {
                        "description": "Category Params",
                        "name": "id",
                        "in": "body",
                        "required": true,
                        "schema": {
                            "$ref": "#/definitions/handler.CategoryReq"
                        }
                    }
                ],
                "responses": {
                    "200": {
                        "description": "OK",
                        "schema": {
                            "type": "string"
                        }
                    }
                }
            }
        },
        "/categories/:id/products": {
            "get": {
                "description": "get Category by Id",
                "consumes": [
                    "application/json"
                ],
                "produces": [
                    "application/json"
                ],
                "tags": [
                    "Category"
                ],
                "summary": "List All Products In Category",
                "parameters": [
                    {
                        "type": "integer",
                        "description": "Category ID",
                        "name": "id",
                        "in": "path",
                        "required": true
                    }
                ],
                "responses": {
                    "200": {
                        "description": "OK",
                        "schema": {
                            "type": "array",
                            "items": {
                                "$ref": "#/definitions/db.Category"
                            }
                        }
                    }
                }
            },
            "post": {
                "description": "Create A Product Within A Category",
                "consumes": [
                    "application/json"
                ],
                "produces": [
                    "application/json"
                ],
                "tags": [
                    "Product"
                ],
                "summary": "Create A Product",
                "parameters": [
                    {
                        "type": "integer",
                        "description": "Product ID",
                        "name": "id",
                        "in": "path",
                        "required": true
                    },
                    {
                        "description": "Category Params",
                        "name": "id",
                        "in": "body",
                        "required": true,
                        "schema": {
                            "$ref": "#/definitions/handler.ProductReq"
                        }
                    },
                    {
                        "type": "string",
                        "description": "Authorization",
                        "name": "Authorization",
                        "in": "header"
                    }
                ],
                "responses": {
                    "200": {
                        "description": "OK",
                        "schema": {
                            "$ref": "#/definitions/db.CreateProductParams"
                        }
                    }
                }
            }
        },
        "/categories/{id}": {
            "get": {
                "description": "get Category by Id",
                "consumes": [
                    "application/json"
                ],
                "produces": [
                    "application/json"
                ],
                "tags": [
                    "Category",
                    "Product"
                ],
                "summary": "Get A Category By ID",
                "parameters": [
                    {
                        "type": "integer",
                        "description": "Category ID",
                        "name": "id",
                        "in": "path",
                        "required": true
                    }
                ],
                "responses": {
                    "200": {
                        "description": "OK",
                        "schema": {
                            "$ref": "#/definitions/handler.CategoryRes"
                        }
                    }
                }
            }
        },
        "/healthz": {
            "post": {
                "description": "Useful to preform a health-check",
                "consumes": [
                    "application/json"
                ],
                "produces": [
                    "application/json"
                ],
                "tags": [
                    "Status"
                ],
                "summary": "Get API Status",
                "responses": {
                    "200": {
                        "description": "One small step...",
                        "schema": {
                            "type": "string"
                        }
                    }
                }
            }
        },
        "/login": {
            "post": {
                "description": "Send credentials to get login token",
                "consumes": [
                    "application/json"
                ],
                "produces": [
                    "application/json"
                ],
                "tags": [
                    "Auth"
                ],
                "summary": "Login using API",
                "parameters": [
                    {
                        "description": "Login Request",
                        "name": "request",
                        "in": "body",
                        "required": true,
                        "schema": {
                            "$ref": "#/definitions/shared.LoginRequest"
                        }
                    }
                ],
                "responses": {
                    "200": {
                        "description": "OK",
                        "schema": {
                            "type": "string"
                        }
                    }
                }
            }
        },
        "/orders": {
            "get": {
                "description": "Get All Orders in DB",
                "consumes": [
                    "application/json"
                ],
                "produces": [
                    "application/json"
                ],
                "tags": [
                    "Orders"
                ],
                "summary": "List Orders",
                "responses": {
                    "200": {
                        "description": "OK",
                        "schema": {
                            "type": "array",
                            "items": {
                                "$ref": "#/definitions/db.ListOrdersRow"
                            }
                        }
                    }
                }
            }
        },
        "/products": {
            "get": {
                "description": "Get All Products in DB",
                "consumes": [
                    "application/json"
                ],
                "produces": [
                    "application/json"
                ],
                "tags": [
                    "Product"
                ],
                "summary": "List Products",
                "responses": {
                    "200": {
                        "description": "OK",
                        "schema": {
                            "type": "array",
                            "items": {
                                "$ref": "#/definitions/handler.ProductRes"
                            }
                        }
                    }
                }
            }
        },
        "/products/{id}": {
            "get": {
                "security": [
                    {
                        "ApiKeyAuth": []
                    }
                ],
                "description": "get Product by Id",
                "consumes": [
                    "application/json"
                ],
                "produces": [
                    "application/json"
                ],
                "tags": [
                    "Product"
                ],
                "summary": "Get A Product By ID",
                "parameters": [
                    {
                        "type": "integer",
                        "description": "Product ID",
                        "name": "id",
                        "in": "path",
                        "required": true
                    },
                    {
                        "type": "string",
                        "description": "Authorization",
                        "name": "Authorization",
                        "in": "header"
                    }
                ],
                "responses": {
                    "200": {
                        "description": "OK",
                        "schema": {
                            "$ref": "#/definitions/handler.ProductRes"
                        }
                    }
                }
            },
            "patch": {
                "security": [
                    {
                        "ApiKeyAuth": []
                    }
                ],
                "description": "Update Product by Id",
                "consumes": [
                    "application/json"
                ],
                "produces": [
                    "application/json"
                ],
                "tags": [
                    "Product"
                ],
                "summary": "Update A Product",
                "parameters": [
                    {
                        "type": "integer",
                        "description": "Product ID",
                        "name": "id",
                        "in": "path",
                        "required": true
                    },
                    {
                        "type": "string",
                        "description": "Authorization",
                        "name": "Authorization",
                        "in": "header"
                    },
                    {
                        "description": "Update Product Params",
                        "name": "id",
                        "in": "body",
                        "required": true,
                        "schema": {
                            "$ref": "#/definitions/handler.ProductReq"
                        }
                    }
                ],
                "responses": {
                    "200": {
                        "description": "OK",
                        "schema": {
                            "type": "string"
                        }
                    }
                }
            }
        },
        "/products/{id}/images": {
            "get": {
                "security": [
                    {
                        "ApiKeyAuth": []
                    }
                ],
                "description": "Retrieve All Images for the Product with This ID",
                "consumes": [
                    "application/json"
                ],
                "produces": [
                    "application/json"
                ],
                "tags": [
                    "Product"
                ],
                "summary": "Get All Images for a product",
                "parameters": [
                    {
                        "type": "integer",
                        "description": "Product ID",
                        "name": "id",
                        "in": "path",
                        "required": true
                    },
                    {
                        "type": "string",
                        "description": "Authorization",
                        "name": "Authorization",
                        "in": "header"
                    },
                    {
                        "type": "file",
                        "description": "image to upload",
                        "name": "image",
                        "in": "formData",
                        "required": true
                    }
                ],
                "responses": {
                    "200": {
                        "description": "OK",
                        "schema": {
                            "type": "string"
                        }
                    },
                    "default": {
                        "description": "",
                        "schema": {
                            "type": "array",
                            "items": {
                                "$ref": "#/definitions/db.ProductImage"
                            }
                        }
                    }
                }
            },
            "post": {
                "security": [
                    {
                        "ApiKeyAuth": []
                    }
                ],
                "description": "Upload An Image for the Product with This ID",
                "consumes": [
                    "application/json"
                ],
                "produces": [
                    "application/json"
                ],
                "tags": [
                    "Product"
                ],
                "summary": "Upload Image And Set As Thumbnail Product",
                "parameters": [
                    {
                        "type": "integer",
                        "description": "Product ID",
                        "name": "id",
                        "in": "path",
                        "required": true
                    },
                    {
                        "type": "string",
                        "description": "Authorization",
                        "name": "Authorization",
                        "in": "header"
                    },
                    {
                        "type": "file",
                        "description": "image to upload",
                        "name": "image",
                        "in": "formData",
                        "required": true
                    }
                ],
                "responses": {
                    "200": {
                        "description": "OK",
                        "schema": {
                            "type": "string"
                        }
                    },
                    "default": {
                        "description": "",
                        "schema": {
                            "type": "string"
                        }
                    }
                }
            }
        },
        "/products/{id}/thumbnail": {
            "get": {
                "security": [
                    {
                        "ApiKeyAuth": []
                    }
                ],
                "description": "Retrieve The Product Image that was Set as the thumbnail",
                "consumes": [
                    "application/json"
                ],
                "produces": [
                    "application/json"
                ],
                "tags": [
                    "Product"
                ],
                "summary": "Get Product's Thumbnail",
                "parameters": [
                    {
                        "type": "integer",
                        "description": "Product ID",
                        "name": "id",
                        "in": "path",
                        "required": true
                    },
                    {
                        "type": "string",
                        "description": "Authorization",
                        "name": "Authorization",
                        "in": "header"
                    }
                ],
                "responses": {
                    "200": {
                        "description": "OK",
                        "schema": {
                            "$ref": "#/definitions/db.ProductImage"
                        }
                    }
                }
            },
            "post": {
                "security": [
                    {
                        "ApiKeyAuth": []
                    }
                ],
                "description": "Update Product by Id",
                "consumes": [
                    "application/json"
                ],
                "produces": [
                    "application/json"
                ],
                "tags": [
                    "Product"
                ],
                "summary": "Upload Image And Set As Thumbnail Product",
                "parameters": [
                    {
                        "type": "integer",
                        "description": "Product ID",
                        "name": "id",
                        "in": "path",
                        "required": true
                    },
                    {
                        "type": "string",
                        "description": "Authorization",
                        "name": "Authorization",
                        "in": "header"
                    },
                    {
                        "type": "file",
                        "description": "image to upload",
                        "name": "image",
                        "in": "formData",
                        "required": true
                    }
                ],
                "responses": {
                    "200": {
                        "description": "OK",
                        "schema": {
                            "type": "string"
                        }
                    },
                    "default": {
                        "description": "",
                        "schema": {
                            "type": "string"
                        }
                    }
                }
            }
        },
        "/register": {
            "post": {
                "description": "Send credentials to get token",
                "consumes": [
                    "application/json"
                ],
                "produces": [
                    "application/json"
                ],
                "tags": [
                    "Auth"
                ],
                "summary": "Register using API",
                "parameters": [
                    {
                        "description": "Registration Request",
                        "name": "request",
                        "in": "body",
                        "required": true,
                        "schema": {
                            "$ref": "#/definitions/shared.RegistrationRequest"
                        }
                    }
                ],
                "responses": {
                    "200": {
                        "description": "OK",
                        "schema": {
                            "type": "string"
                        }
                    }
                }
            }
        },
        "/sales/seller/:id": {
            "get": {
                "description": "Get Seller Sales Statistics",
                "consumes": [
                    "application/json"
                ],
                "produces": [
                    "application/json"
                ],
                "tags": [
                    "Orders",
                    "Stats",
                    "User"
                ],
                "summary": "Get Seller Sales Stats",
                "responses": {
                    "200": {
                        "description": "OK",
                        "schema": {
                            "$ref": "#/definitions/handler.SellerStats"
                        }
                    }
                }
            },
            "post": {
                "description": "Get Product Sales Statistics for a given time range",
                "consumes": [
                    "application/json"
                ],
                "produces": [
                    "application/json"
                ],
                "tags": [
                    "Product",
                    "Orders",
                    "Stats",
                    "User"
                ],
                "summary": "Get Product Sales",
                "parameters": [
                    {
                        "description": "Seller Stats Request",
                        "name": "request",
                        "in": "body",
                        "required": true,
                        "schema": {
                            "$ref": "#/definitions/handler.SellerStatsRequest"
                        }
                    }
                ],
                "responses": {
                    "200": {
                        "description": "OK",
                        "schema": {
                            "$ref": "#/definitions/handler.SellerStats"
                        }
                    }
                }
            }
        },
        "/sales/seller/:id/products": {
            "get": {
                "description": "Get All Orders in DB",
                "consumes": [
                    "application/json"
                ],
                "produces": [
                    "application/json"
                ],
                "tags": [
                    "Orders"
                ],
                "summary": "List User Orders Sold",
                "responses": {
                    "200": {
                        "description": "OK",
                        "schema": {
                            "type": "array",
                            "items": {
                                "$ref": "#/definitions/handler.SellerOrderRes"
                            }
                        }
                    }
                }
            }
        },
        "/user/:id/orders": {
            "post": {
                "description": "Create An Order in DB",
                "consumes": [
                    "application/json"
                ],
                "produces": [
                    "application/json"
                ],
                "tags": [
                    "Orders"
                ],
                "summary": "Create Order",
                "parameters": [
                    {
                        "description": "Order Request",
                        "name": "id",
                        "in": "body",
                        "required": true,
                        "schema": {
                            "$ref": "#/definitions/handler.OrdersRequest"
                        }
                    }
                ],
                "responses": {
                    "200": {
                        "description": "OK",
                        "schema": {
                            "type": "array",
                            "items": {
                                "type": "string"
                            }
                        }
                    },
                    "404": {
                        "description": "Not Found",
                        "schema": {
                            "type": "array",
                            "items": {
                                "type": "string"
                            }
                        }
                    }
                }
            }
        },
        "/user/:id/orders/:orderId/cancel": {
            "post": {
                "description": "Cancel An Order",
                "consumes": [
                    "application/json"
                ],
                "produces": [
                    "application/json"
                ],
                "tags": [
                    "Orders"
                ],
                "summary": "Cancel Order",
                "parameters": [
                    {
                        "type": "string",
                        "description": "User ID",
                        "name": "id",
                        "in": "path",
                        "required": true
                    },
                    {
                        "description": "Order ID",
                        "name": "id",
                        "in": "body",
                        "required": true,
                        "schema": {
                            "type": "string"
                        }
                    }
                ],
                "responses": {
                    "200": {
                        "description": "OK",
                        "schema": {
                            "type": "string"
                        }
                    },
                    "500": {
                        "description": "Internal Server Error",
                        "schema": {
                            "type": "string"
                        }
                    }
                }
            }
        },
        "/user/:id/orders/:orderId/deliver": {
            "post": {
                "description": "Deliver An Order",
                "consumes": [
                    "application/json"
                ],
                "produces": [
                    "application/json"
                ],
                "tags": [
                    "Orders"
                ],
                "summary": "Deliver Order",
                "parameters": [
                    {
                        "type": "string",
                        "description": "User ID",
                        "name": "id",
                        "in": "path",
                        "required": true
                    },
                    {
                        "description": "Order ID",
                        "name": "id",
                        "in": "body",
                        "required": true,
                        "schema": {
                            "type": "string"
                        }
                    }
                ],
                "responses": {
                    "200": {
                        "description": "OK",
                        "schema": {
                            "type": "string"
                        }
                    },
                    "500": {
                        "description": "Internal Server Error",
                        "schema": {
                            "type": "string"
                        }
                    }
                }
            }
        },
        "/user/:id/orders/:orderId/ship": {
            "post": {
                "description": "Ship An Order",
                "consumes": [
                    "application/json"
                ],
                "produces": [
                    "application/json"
                ],
                "tags": [
                    "Orders"
                ],
                "summary": "Ship Order",
                "parameters": [
                    {
                        "type": "string",
                        "description": "User ID",
                        "name": "id",
                        "in": "path",
                        "required": true
                    },
                    {
                        "description": "Order ID",
                        "name": "id",
                        "in": "body",
                        "required": true,
                        "schema": {
                            "type": "string"
                        }
                    }
                ],
                "responses": {
                    "200": {
                        "description": "OK",
                        "schema": {
                            "type": "string"
                        }
                    },
                    "500": {
                        "description": "Internal Server Error",
                        "schema": {
                            "type": "string"
                        }
                    }
                }
            }
        },
        "/user/{id}/cart": {
            "get": {
                "description": "Get All Products in User's Cart",
                "consumes": [
                    "application/json"
                ],
                "produces": [
                    "application/json"
                ],
                "tags": [
                    "User",
                    "Product"
                ],
                "summary": "Get Products in User's Cart",
                "parameters": [
                    {
                        "type": "string",
                        "description": "User ID",
                        "name": "id",
                        "in": "path",
                        "required": true
                    }
                ],
                "responses": {
                    "200": {
                        "description": "OK",
                        "schema": {
                            "type": "array",
                            "items": {
                                "$ref": "#/definitions/db.GetUserCartItemsRow"
                            }
                        }
                    }
                }
            },
            "post": {
                "description": "Add a Product to cart or Modify Product in cart by updating it's quanity",
                "consumes": [
                    "application/json"
                ],
                "produces": [
                    "application/json"
                ],
                "tags": [
                    "User",
                    "Product"
                ],
                "summary": "Add A Product to User's Cart",
                "parameters": [
                    {
                        "type": "string",
                        "description": "User ID",
                        "name": "id",
                        "in": "path",
                        "required": true
                    },
                    {
                        "description": "Product Cart Request",
                        "name": "id",
                        "in": "body",
                        "required": true,
                        "schema": {
                            "$ref": "#/definitions/handler.ProductCartRequest"
                        }
                    }
                ],
                "responses": {
                    "200": {
                        "description": "OK",
                        "schema": {
                            "type": "array",
                            "items": {
                                "type": "string"
                            }
                        }
                    }
                }
            },
            "patch": {
                "description": "Modify Product in cart by updating it's quanity",
                "consumes": [
                    "application/json"
                ],
                "produces": [
                    "application/json"
                ],
                "tags": [
                    "User",
                    "Product"
                ],
                "summary": "Update A Product in User's Cart",
                "parameters": [
                    {
                        "type": "string",
                        "description": "User ID",
                        "name": "id",
                        "in": "path",
                        "required": true
                    },
                    {
                        "description": "Product Cart Request",
                        "name": "id",
                        "in": "body",
                        "required": true,
                        "schema": {
                            "$ref": "#/definitions/handler.ProductCartRequest"
                        }
                    }
                ],
                "responses": {
                    "200": {
                        "description": "OK",
                        "schema": {
                            "type": "array",
                            "items": {
                                "type": "string"
                            }
                        }
                    }
                }
            }
        },
        "/user/{id}/cart/{productId}": {
            "delete": {
                "description": "Delete A Product From The User's Cart",
                "consumes": [
                    "application/json"
                ],
                "produces": [
                    "application/json"
                ],
                "tags": [
                    "User",
                    "Product"
                ],
                "summary": "Delete Cart Item",
                "parameters": [
                    {
                        "type": "string",
                        "description": "User ID",
                        "name": "id",
                        "in": "path",
                        "required": true
                    },
                    {
                        "type": "string",
                        "description": "Product ID",
                        "name": "id",
                        "in": "path",
                        "required": true
                    }
                ],
                "responses": {
                    "200": {
                        "description": "OK",
                        "schema": {
                            "type": "array",
                            "items": {
                                "type": "string"
                            }
                        }
                    }
                }
            }
        },
        "/user/{id}/favorites": {
            "get": {
                "description": "Get A List Of All Products that have been favorited by the user",
                "consumes": [
                    "application/json"
                ],
                "produces": [
                    "application/json"
                ],
                "tags": [
                    "User",
                    "Product"
                ],
                "summary": "List Products Favorited By User",
                "parameters": [
                    {
                        "type": "string",
                        "description": "User ID",
                        "name": "id",
                        "in": "path",
                        "required": true
                    }
                ],
                "responses": {
                    "200": {
                        "description": "OK",
                        "schema": {
                            "type": "array",
                            "items": {
                                "type": "string"
                            }
                        }
                    }
                }
            }
        },
        "/user/{id}/favorites/{productId}": {
            "post": {
                "description": "Favorite A Product Using Product and User ID",
                "consumes": [
                    "application/json"
                ],
                "produces": [
                    "application/json"
                ],
                "tags": [
                    "User",
                    "Product"
                ],
                "summary": "Favorite A Product for user",
                "parameters": [
                    {
                        "type": "string",
                        "description": "User ID",
                        "name": "id",
                        "in": "path",
                        "required": true
                    },
                    {
                        "type": "string",
                        "description": "Product ID",
                        "name": "productId",
                        "in": "path",
                        "required": true
                    }
                ],
                "responses": {
                    "200": {
                        "description": "OK",
                        "schema": {
                            "type": "array",
                            "items": {
                                "type": "string"
                            }
                        }
                    }
                }
            },
            "delete": {
                "description": "Remove a product from a user's favorites list",
                "consumes": [
                    "application/json"
                ],
                "produces": [
                    "application/json"
                ],
                "tags": [
                    "User",
                    "Product"
                ],
                "summary": "Remove Product from Favorites",
                "parameters": [
                    {
                        "type": "string",
                        "description": "User ID",
                        "name": "id",
                        "in": "path",
                        "required": true
                    },
                    {
                        "type": "string",
                        "description": "Product ID",
                        "name": "productId",
                        "in": "path",
                        "required": true
                    }
                ],
                "responses": {
                    "200": {
                        "description": "OK",
                        "schema": {
                            "type": "array",
                            "items": {
                                "type": "string"
                            }
                        }
                    }
                }
            }
        },
        "/user/{id}/orders": {
            "get": {
                "description": "Get All User's Orders in DB",
                "consumes": [
                    "application/json"
                ],
                "produces": [
                    "application/json"
                ],
                "tags": [
                    "Orders"
                ],
                "summary": "List Orders made by a user",
                "parameters": [
                    {
                        "type": "string",
                        "description": "User ID",
                        "name": "id",
                        "in": "path",
                        "required": true
                    }
                ],
                "responses": {
                    "200": {
                        "description": "OK",
                        "schema": {
                            "type": "array",
                            "items": {
                                "$ref": "#/definitions/db.GetUserOrdersRow"
                            }
                        }
                    }
                }
            }
        }
    },
    "definitions": {
        "big.Int": {
            "type": "object"
        },
        "db.Category": {
            "type": "object",
            "properties": {
                "backgroundUrl": {
                    "$ref": "#/definitions/pgtype.Text"
                },
                "bannerUrl": {
                    "$ref": "#/definitions/pgtype.Text"
                },
                "createdAt": {
                    "$ref": "#/definitions/pgtype.Timestamp"
                },
                "description": {
                    "$ref": "#/definitions/pgtype.Text"
                },
                "id": {
                    "type": "integer"
                },
                "name": {
                    "type": "string"
                },
                "parentID": {
                    "$ref": "#/definitions/pgtype.Int4"
                },
                "updatedAt": {
                    "$ref": "#/definitions/pgtype.Timestamp"
                }
            }
        },
        "db.CategoryAttribute": {
            "type": "object",
            "properties": {
                "attributeTypeID": {
                    "$ref": "#/definitions/pgtype.Int4"
                },
                "categoryID": {
                    "$ref": "#/definitions/pgtype.Int4"
                },
                "enumValues": {
                    "type": "array",
                    "items": {
                        "type": "string"
                    }
                },
                "id": {
                    "type": "integer"
                },
                "isRequired": {
                    "$ref": "#/definitions/pgtype.Bool"
                },
                "name": {
                    "type": "string"
                }
            }
        },
        "db.CreateCategoryAttributeParams": {
            "type": "object",
            "properties": {
                "attributeTypeID": {
                    "$ref": "#/definitions/pgtype.Int4"
                },
                "categoryID": {
                    "$ref": "#/definitions/pgtype.Int4"
                },
                "enumValues": {
                    "type": "array",
                    "items": {
                        "type": "string"
                    }
                },
                "isRequired": {
                    "$ref": "#/definitions/pgtype.Bool"
                },
                "name": {
                    "type": "string"
                }
            }
        },
        "db.CreateProductParams": {
            "type": "object",
            "properties": {
                "description": {
                    "$ref": "#/definitions/pgtype.Text"
                },
                "discountPrice": {
                    "$ref": "#/definitions/pgtype.Numeric"
                },
                "price": {
                    "$ref": "#/definitions/pgtype.Numeric"
                },
                "profileID": {
                    "$ref": "#/definitions/pgtype.Text"
                },
                "quantity": {
                    "type": "integer"
                },
                "regularPrice": {
                    "$ref": "#/definitions/pgtype.Numeric"
                },
                "shortDescription": {
                    "$ref": "#/definitions/pgtype.Text"
                },
                "title": {
                    "type": "string"
                },
                "type": {
                    "$ref": "#/definitions/pgtype.Text"
                }
            }
        },
        "db.GetSellerOrderItemsRow": {
            "type": "object",
            "properties": {
                "id": {
                    "type": "integer"
                },
                "price": {
                    "$ref": "#/definitions/pgtype.Numeric"
                },
                "productID": {
                    "type": "integer"
                },
                "quantity": {
                    "type": "integer"
                }
            }
        },
        "db.GetUserCartItemsRow": {
            "type": "object",
            "properties": {
                "id": {
                    "type": "integer"
                },
                "price": {
                    "$ref": "#/definitions/pgtype.Numeric"
                },
                "profileID": {
                    "$ref": "#/definitions/pgtype.Text"
                },
                "quantity": {
                    "type": "integer"
                },
                "shortDescription": {
                    "$ref": "#/definitions/pgtype.Text"
                },
                "title": {
                    "type": "string"
                }
            }
        },
        "db.GetUserOrdersRow": {
            "type": "object",
            "properties": {
                "createdAt": {
                    "$ref": "#/definitions/pgtype.Timestamp"
                },
                "id": {
                    "type": "integer"
                },
                "profileID": {
                    "type": "string"
                },
                "statusID": {
                    "type": "integer"
                },
                "statusName": {
                    "type": "string"
                },
                "thumbnailUrl": {
                    "$ref": "#/definitions/pgtype.Text"
                },
                "updatedAt": {
                    "$ref": "#/definitions/pgtype.Timestamp"
                }
            }
        },
        "db.ListOrdersRow": {
            "type": "object",
            "properties": {
                "createdAt": {
                    "$ref": "#/definitions/pgtype.Timestamp"
                },
                "id": {
                    "$ref": "#/definitions/pgtype.Int4"
                },
                "profileID": {
                    "$ref": "#/definitions/pgtype.Text"
                },
                "statusID": {
                    "type": "integer"
                },
                "statusName": {
                    "type": "string"
                },
                "updatedAt": {
                    "$ref": "#/definitions/pgtype.Timestamp"
                }
            }
        },
        "db.ProductImage": {
            "type": "object",
            "properties": {
                "createdAt": {
                    "$ref": "#/definitions/pgtype.Timestamp"
                },
                "id": {
                    "type": "integer"
                },
                "imageUrl": {
                    "type": "string"
                },
                "productID": {
                    "type": "integer"
                }
            }
        },
        "db.UpdateAttributeParams": {
            "type": "object",
            "properties": {
                "attributeTypeID": {
                    "$ref": "#/definitions/pgtype.Int4"
                },
                "categoryID": {
                    "$ref": "#/definitions/pgtype.Int4"
                },
                "enumValues": {
                    "type": "array",
                    "items": {
                        "type": "string"
                    }
                },
                "id": {
                    "type": "integer"
                },
                "isRequired": {
                    "$ref": "#/definitions/pgtype.Bool"
                },
                "name": {
                    "type": "string"
                }
            }
        },
        "handler.CategoryReq": {
            "type": "object",
            "properties": {
                "Description": {
                    "type": "string"
                },
                "Name": {
                    "type": "string"
                },
                "ParentID": {
                    "type": "integer"
                }
            }
        },
        "handler.CategoryRes": {
            "type": "object",
            "properties": {
                "attributes": {
                    "type": "array",
                    "items": {
                        "$ref": "#/definitions/db.CategoryAttribute"
                    }
                },
                "backgroundUrl": {
                    "$ref": "#/definitions/pgtype.Text"
                },
                "bannerUrl": {
                    "$ref": "#/definitions/pgtype.Text"
                },
                "createdAt": {
                    "$ref": "#/definitions/pgtype.Timestamp"
                },
                "description": {
                    "$ref": "#/definitions/pgtype.Text"
                },
                "id": {
                    "type": "integer"
                },
                "name": {
                    "type": "string"
                },
                "parentID": {
                    "$ref": "#/definitions/pgtype.Int4"
                },
                "products": {
                    "type": "array",
                    "items": {
                        "$ref": "#/definitions/handler.ProductRes"
                    }
                },
                "updatedAt": {
                    "$ref": "#/definitions/pgtype.Timestamp"
                }
            }
        },
        "handler.CreateOrderProductsRequest": {
            "type": "object",
            "properties": {
                "ID": {
                    "type": "integer"
                },
                "Quantity": {
                    "type": "integer"
                }
            }
        },
        "handler.OrdersRequest": {
            "type": "object",
            "properties": {
                "products": {
                    "type": "array",
                    "items": {
                        "$ref": "#/definitions/handler.CreateOrderProductsRequest"
                    }
                }
            }
        },
        "handler.ProductCartRequest": {
            "type": "object",
            "properties": {
                "ProductID": {
                    "type": "integer"
                },
                "ProductQuantity": {
                    "type": "integer"
                }
            }
        },
        "handler.ProductCategoryRes": {
            "type": "object",
            "properties": {
                "ID": {
                    "type": "integer"
                },
                "Name": {
                    "type": "string"
                }
            }
        },
        "handler.ProductExternalDetails": {
            "type": "object",
            "properties": {
                "BrandID": {
                    "type": "string"
                },
                "BrandImageURL": {
                    "type": "string"
                },
                "BrandName": {
                    "type": "string"
                },
                "ExternalURL": {
                    "type": "string"
                }
            }
        },
        "handler.ProductReq": {
            "type": "object",
            "properties": {
                "Description": {
                    "type": "string"
                },
                "DiscountPrice": {
                    "type": "number"
                },
                "Price": {
                    "type": "number"
                },
                "ProfileID": {
                    "type": "string"
                },
                "Quantity": {
                    "type": "integer"
                },
                "RegularPrice": {
                    "type": "number"
                },
                "ShortDescription": {
                    "type": "string"
                },
                "Title": {
                    "type": "string"
                },
                "Type": {
                    "type": "string"
                }
            }
        },
        "handler.ProductRes": {
            "type": "object",
            "properties": {
                "Category": {
                    "$ref": "#/definitions/handler.ProductCategoryRes"
                },
                "ExternalDetails": {
                    "$ref": "#/definitions/handler.ProductExternalDetails"
                },
                "Images": {
                    "type": "array",
                    "items": {
                        "$ref": "#/definitions/db.ProductImage"
                    }
                },
                "Thumbnail_url": {
                    "type": "string"
                },
                "createdAt": {
                    "$ref": "#/definitions/pgtype.Timestamp"
                },
                "description": {
                    "$ref": "#/definitions/pgtype.Text"
                },
                "discountPrice": {
                    "$ref": "#/definitions/pgtype.Numeric"
                },
                "id": {
                    "type": "integer"
                },
                "price": {
                    "$ref": "#/definitions/pgtype.Numeric"
                },
                "profileID": {
                    "$ref": "#/definitions/pgtype.Text"
                },
                "quantity": {
                    "type": "integer"
                },
                "regularPrice": {
                    "$ref": "#/definitions/pgtype.Numeric"
                },
                "shortDescription": {
                    "$ref": "#/definitions/pgtype.Text"
                },
                "title": {
                    "type": "string"
                },
                "type": {
                    "$ref": "#/definitions/pgtype.Text"
                },
                "updatedAt": {
                    "$ref": "#/definitions/pgtype.Timestamp"
                }
            }
        },
        "handler.SellerOrderRes": {
            "type": "object",
            "properties": {
                "Items": {
                    "type": "array",
                    "items": {
                        "$ref": "#/definitions/db.GetSellerOrderItemsRow"
                    }
                },
                "buyerProfileID": {
                    "type": "string"
                },
                "orderCreatedAt": {
                    "$ref": "#/definitions/pgtype.Timestamp"
                },
                "orderID": {
                    "type": "integer"
                },
                "orderUpdatedAt": {
                    "$ref": "#/definitions/pgtype.Timestamp"
                },
                "statusID": {
                    "type": "integer"
                },
                "statusName": {
                    "type": "string"
                },
                "thumbnailUrl": {}
            }
        },
        "handler.SellerStats": {
            "type": "object",
            "properties": {
                "topProducts": {
                    "type": "array",
                    "items": {
                        "$ref": "#/definitions/handler.TopProduct"
                    }
                },
                "totalOrders": {
                    "type": "integer"
                },
                "totalProductsSold": {
                    "type": "integer"
                },
                "totalRevenue": {
                    "type": "number"
                }
            }
        },
        "handler.SellerStatsRequest": {
            "type": "object",
            "properties": {
                "end": {
                    "type": "string"
                },
                "start": {
                    "type": "string"
                }
            }
        },
        "handler.TopProduct": {
            "type": "object",
            "properties": {
                "id": {
                    "type": "integer"
                },
                "revenue": {
                    "type": "number"
                },
                "title": {
                    "type": "string"
                },
                "totalSold": {
                    "type": "integer"
                }
            }
        },
        "pgtype.Bool": {
            "type": "object",
            "properties": {
                "bool": {
                    "type": "boolean"
                },
                "valid": {
                    "type": "boolean"
                }
            }
        },
        "pgtype.InfinityModifier": {
            "type": "integer",
            "enum": [
                1,
                0,
                -1
            ],
            "x-enum-varnames": [
                "Infinity",
                "Finite",
                "NegativeInfinity"
            ]
        },
        "pgtype.Int4": {
            "type": "object",
            "properties": {
                "int32": {
                    "type": "integer"
                },
                "valid": {
                    "type": "boolean"
                }
            }
        },
        "pgtype.Numeric": {
            "type": "object",
            "properties": {
                "exp": {
                    "type": "integer"
                },
                "infinityModifier": {
                    "$ref": "#/definitions/pgtype.InfinityModifier"
                },
                "int": {
                    "$ref": "#/definitions/big.Int"
                },
                "naN": {
                    "type": "boolean"
                },
                "valid": {
                    "type": "boolean"
                }
            }
        },
        "pgtype.Text": {
            "type": "object",
            "properties": {
                "string": {
                    "type": "string"
                },
                "valid": {
                    "type": "boolean"
                }
            }
        },
        "pgtype.Timestamp": {
            "type": "object",
            "properties": {
                "infinityModifier": {
                    "$ref": "#/definitions/pgtype.InfinityModifier"
                },
                "time": {
                    "description": "Time zone will be ignored when encoding to PostgreSQL.",
                    "type": "string"
                },
                "valid": {
                    "type": "boolean"
                }
            }
        },
        "shared.LoginRequest": {
            "type": "object",
            "required": [
                "password",
                "username"
            ],
            "properties": {
                "password": {
                    "type": "string"
                },
                "username": {
                    "type": "string"
                }
            }
        },
        "shared.RegistrationRequest": {
            "type": "object",
            "required": [
                "email",
                "firstName",
                "lastName",
                "password",
                "username"
            ],
            "properties": {
                "email": {
                    "type": "string"
                },
                "firstName": {
                    "type": "string",
                    "maxLength": 30,
                    "minLength": 1
                },
                "lastName": {
                    "type": "string",
                    "maxLength": 30,
                    "minLength": 1
                },
                "password": {
                    "type": "string"
                },
                "username": {
                    "type": "string",
                    "maxLength": 16,
                    "minLength": 3
                }
            }
        }
    },
    "securityDefinitions": {
        "BearerAuth": {
            "type": "apiKey",
            "name": "Authorization",
            "in": "header"
        }
    }
}